nsj_gcf_utils/__init__.py
nsj_gcf_utils/abstract_repository.py
nsj_gcf_utils/app_logger.py
nsj_gcf_utils/authentication_service.py
nsj_gcf_utils/db_adapter.py
nsj_gcf_utils/db_adapter2.py
nsj_gcf_utils/dto_util.py
nsj_gcf_utils/exception.py
nsj_gcf_utils/hash_util.py
nsj_gcf_utils/http_util.py
nsj_gcf_utils/iban.py
nsj_gcf_utils/json_util.py
nsj_gcf_utils/keycloak_service.py
nsj_gcf_utils/log_time.py
nsj_gcf_utils/logger.py
nsj_gcf_utils/nsj_authentication_service.py
nsj_gcf_utils/pagination_util.py
nsj_gcf_utils/rest_error_util.py
nsj_gcf_utils/router.py
nsj_gcf_utils/sql_utils.py
nsj_gcf_utils-1.1.0.dist-info/licenses/LICENSE
nsj_gcf_utils-1.1.0.dist-info/METADATA
nsj_gcf_utils-1.1.0.dist-info/WHEEL
nsj_gcf_utils-1.1.0.dist-info/top_level.txt
nsj_gcf_utils-1.1.0.dist-info/RECORD
