Metadata-Version: 2.4
Name: nsj_gcf_utils
Version: 1.1.0
Summary: Utilitários para construção de Google Cloud Functions.
Home-page: https://github.com/Nasajon/nsj_gcf_utils
Author: Nasajon Sistemas
Author-email: contact.dev@nasajon.com.br
Project-URL: Source, https://github.com/Nasajon/nsj_gcf_utils
Classifier: Development Status :: 3 - Alpha
Classifier: Intended Audience :: Developers
Classifier: Topic :: Software Development :: Build Tools
Classifier: Programming Language :: Python :: 3
Requires-Python: >=3.4
License-File: LICENSE
Requires-Dist: requests>=2.26.0
Requires-Dist: sqlparams>=3.0.0
Requires-Dist: pydantic>=1.9.0
Requires-Dist: python_dateutil<3.0.0,>=2.9.0
Dynamic: license-file
